pytest_apiver-0.1.0.dist-info/METADATA
pytest_apiver-0.1.0.dist-info/WHEEL
pytest_apiver-0.1.0.dist-info/entry_points.txt
pytest_apiver/__init__.py
pytest_apiver/_internal/__init__.py
pytest_apiver/plugin.py
pytest_apiver/py.typed
pytest_apiver-0.1.0.dist-info/RECORD
