Metadata-Version: 2.1
Name: pytest-apiver
Version: 0.1.0
Author-Email: Reef Technologies <opensource@reef.pl>
License: MIT
Classifier: Intended Audience :: Developers
Classifier: Topic :: Software Development :: Libraries
Classifier: License :: OSI Approved :: MIT License
Classifier: Programming Language :: Python :: 3
Classifier: Programming Language :: Python :: 3.9
Classifier: Programming Language :: Python :: 3.11
Classifier: Programming Language :: Python :: 3.12
Project-URL: Source, https://github.com/reef-technologies/pytest_apiver
Project-URL: Issue tracker, https://github.com/reef-technologies/pytest_apiver/issues
Requires-Python: >=3.9
Requires-Dist: pytest
